{"openapi":"3.1.0","info":{"title":"FastAPI","version":"0.1.0"},"paths":{"/api/status":{"get":{"tags":["api"],"summary":"Bot Status","description":"Check the bot's status via a FastAPI endpoint.\n\nReturns\n-------\nIStatus\n    Status.","operationId":"bot_status_api_status_get","responses":{"200":{"description":"Successful Response","content":{"application/json":{"schema":{"$ref":"#/components/schemas/IStatus"}}}}}}},"/api/guilds":{"get":{"tags":["api","guild"],"summary":"Get","description":"Retorna uma lista de guildas disponíveis.\n\nReturns\n-------\nlist[Guild]\n    As guildas.","operationId":"get_api_guilds_get","responses":{"200":{"description":"Successful Response","content":{"application/json":{"schema":{"items":{"$ref":"#/components/schemas/Guild"},"type":"array","title":"Response Get Api Guilds Get"}}}},"404":{"description":"Not found"}}}}},"components":{"schemas":{"Guild":{"properties":{"id":{"type":"integer","title":"Id"},"name":{"type":"string","title":"Name"},"description":{"anyOf":[{"type":"string"},{"type":"null"}],"title":"Description"},"approximate_member_count":{"type":"integer","title":"Approximate Member Count"}},"type":"object","required":["id","name","description","approximate_member_count"],"title":"Guild","description":"Guild model."},"IStatus":{"properties":{"status":{"type":"string","enum":["online","offline"],"title":"Status"}},"type":"object","required":["status"],"title":"IStatus","description":"Estado atual do Bot."}}}}